task3/ram.sv
module ram #(
    parameter ADDRESS_WIDTH = 9,
    parameter DATA_WIDTH = 8
)(
    input logic clk,
    input logic [ADDRESS_WIDTH-1:0] r_addr,
    input logic [ADDRESS_WIDTH-1:0] w_addr,
    input logic r_en,
    input logic w_en,
    input logic [DATA_WIDTH-1:0] din,
    output logic [DATA_WIDTH-1:0] dout,

);
// 3-bit vector with a depth of 2^8 bits
logic [DATA_WIDTH-1:0] ram_array [2**ADDRESS_WIDTH-1:0];

// Initialise memory

always_ff @(posedge clk) begin
    if(r_en == 1) begin
        dout <= ram_array [r_addr];
    end
    if(w_en == 1) begin
        ram_array[w_addr] <= din;
    end
end

endmodule

task3/counter.sv
module counter #(
    // bits in counter set to 8 bits
    parameter WIDTH = 8
)(
    // interface signals
    input logic clk, //clk
    input logic rst, //reset
    input logic en, // enable
    input logic [WIDTH-1:0] offset,//offset
    output logic [WIDTH-1:0] count1, //count output
    output logic [WIDTH-1:0] count2 //count output

);
// indicates that this is a clocked circuit

always_ff @(posedge clk) 
if(rst) begin
    count1 <= 0;
    count2 <= 0;
end
else begin
    count1 <= count1+ 1'b1;
    count2 <= count1 - offset;
end


endmodule

task3/sigdelay.sv
module sigdelay #(
    parameter D_WIDTH = 8,
    parameter A_WIDTH = 8
)(
    input logic clk,
    input logic rst,
    input logic wr,
    input logic rd,
    input logic [D_WIDTH-1:0] offset,
    input logic en,
    output logic [D_WIDTH-1:0] mic_signal,
    output logic [D_WIDTH-1:0] delayed_signal
);

// connecting variables
logic [D_WIDTH-1:0] addr1;
logic [D_WIDTH-1:0] addr2;


counter addrCounter (
    .clk (clk),
    .rst(rst),
    .en(en),
    .offset(offset),
    .count1(addr1),
    .count2(addr2)
);

ram sigram(
    .clk(clk),
    .r_en(rd),
    .w_en(wr),
    .r_addr(addr1),
    .w_addr(addr2),
    .din(mic_signal),
    .dout(delayed_signal)
);
endmodule

task3/sigdelay.vcd
$version Generated by VerilatedVcd $end
$date Sat Oct 29 18:57:17 2022 $end
$timescale 1ps $end

 $scope module TOP $end
  $var wire  1 ' clk $end
  $var wire  8 . delayed_signal [7:0] $end
  $var wire  1 , en $end
  $var wire  8 - mic_signal [7:0] $end
  $var wire  8 + offset [7:0] $end
  $var wire  1 * rd $end
  $var wire  1 ( rst $end
  $var wire  1 ) wr $end
  $scope module sigdelay $end
   $var wire 32 / A_WIDTH [31:0] $end
   $var wire 32 / D_WIDTH [31:0] $end
   $var wire  8 # addr1 [7:0] $end
   $var wire  8 $ addr2 [7:0] $end
   $var wire  1 ' clk $end
   $var wire  8 . delayed_signal [7:0] $end
   $var wire  1 , en $end
   $var wire  8 - mic_signal [7:0] $end
   $var wire  8 + offset [7:0] $end
   $var wire  1 * rd $end
   $var wire  1 ( rst $end
   $var wire  1 ) wr $end
   $scope module addrCounter $end
    $var wire 32 / WIDTH [31:0] $end
    $var wire  1 ' clk $end
    $var wire  8 # count1 [7:0] $end
    $var wire  8 $ count2 [7:0] $end
    $var wire  1 , en $end
    $var wire  8 + offset [7:0] $end
    $var wire  1 ( rst $end
   $upscope $end
   $scope module sigram $end
    $var wire 32 0 ADDRESS_WIDTH [31:0] $end
    $var wire 32 / DATA_WIDTH [31:0] $end
    $var wire  1 ' clk $end
    $var wire  8 - din [7:0] $end
    $var wire  8 . dout [7:0] $end
    $var wire  9 % r_addr [8:0] $end
    $var wire  1 * r_en $end
    $var wire  9 & w_addr [8:0] $end
    $var wire  1 ) w_en $end
   $upscope $end
  $upscope $end
 $upscope $end
$enddefinitions $end


#0
b00000000 #
b00000000 $
b000000000 %
b000000000 &
1'
0(
1)
1*
b01000000 +
0,
b00000000 -
b00000000 .
b00000000000000000000000000001000 /
b00000000000000000000000000001001 0
#1
0'
#2
b00000001 #
b11000000 $
b000000001 %
b011000000 &
1'
b01110110 -
#3
0'
#4
b00000010 #
b11000001 $
b000000010 %
b011000001 &
1'
b01011111 -
#5
0'
#6
b00000011 #
b11000010 $
b000000011 %
b011000010 &
1'
b01001111 -
#7
0'
#8
b00000100 #
b11000011 $
b000000100 %
b011000011 &
1'
b01000000 -
#9
0'
#10
b00000101 #
b11000100 $
b000000101 %
b011000100 &
1'
b00110100 -
#11
0'
#12
b00000110 #
b11000101 $
b000000110 %
b011000101 &
1'
b00101011 -
#13
0'
#14
b00000111 #
b11000110 $
b000000111 %
b011000110 &
1'
b00100111 -
#15
0'
#16
b00001000 #
b11000111 $
b000001000 %
b011000111 &
1'
b00101000 -
#17
0'
#18
b00001001 #
b11001000 $
b000001001 %
b011001000 &
1'
b00101101 -
#19
0'
#20
b00001010 #
b11001001 $
b000001010 %
b011001001 &
1'
b00110110 -
#21
0'
#22
b00001011 #
b11001010 $
b000001011 %
b011001010 &
1'
b01000011 -
#23
0'
#24
b00001100 #
b11001011 $
b000001100 %
b011001011 &
1'
b01010011 -
#25
0'
#26
b00001101 #
b11001100 $
b000001101 %
b011001100 &
1'
b01100010 -
#27
0'
#28
b00001110 #
b11001101 $
b000001110 %
b011001101 &
1'
b01110011 -
#29
0'
#30
b00001111 #
b11001110 $
b000001111 %
b011001110 &
1'
b10000011 -
#31
0'
#32
b00010000 #
b11001111 $
b000010000 %
b011001111 &
1'
b10010010 -
#33
0'
#34
b00010001 #
b11010000 $
b000010001 %
b011010000 &
1'
b10011110 -
#35
0'
#36
b00010010 #
b11010001 $
b000010010 %
b011010001 &
1'
b10101000 -
#37
0'
#38
b00010011 #
b11010010 $
b000010011 %
b011010010 &
1'
b10101101 -
#39
0'
#40
b00010100 #
b11010011 $
b000010100 %
b011010011 &
1'
b10101111 -
#41
0'
#42
b00010101 #
b11010100 $
b000010101 %
b011010100 &
1'
b10101010 -
#43
0'
#44
b00010110 #
b11010101 $
b000010110 %
b011010101 &
1'
b10100000 -
#45
0'
#46
b00010111 #
b11010110 $
b000010111 %
b011010110 &
1'
b10010011 -
#47
0'
#48
b00011000 #
b11010111 $
b000011000 %
b011010111 &
1'
b10000001 -
#49
0'
#50
b00011001 #
b11011000 $
b000011001 %
b011011000 &
1'
b01101110 -
#51
0'
#52
b00011010 #
b11011001 $
b000011010 %
b011011001 &
1'
b01011100 -
#53
0'
#54
b00011011 #
b11011010 $
b000011011 %
b011011010 &
1'
b01001010 -
#55
0'
#56
b00011100 #
b11011011 $
b000011100 %
b011011011 &
1'
b00111100 -
#57
0'
#58
b00011101 #
b11011100 $
b000011101 %
b011011100 &
1'
b00110001 -
#59
0'
#60
b00011110 #
b11011101 $
b000011110 %
b011011101 &
1'
b00101011 -
#61
0'
#62
b00011111 #
b11011110 $
b000011111 %
b011011110 &
1'
b00101000 -
#63
0'
#64
b00100000 #
b11011111 $
b000100000 %
b011011111 &
1'
#65
0'
#66
b00100001 #
b11100000 $
b000100001 %
b011100000 &
1'
b00101110 -
#67
0'
#68
b00100010 #
b11100001 $
b000100010 %
b011100001 &
1'
b00111001 -
#69
0'
#70
b00100011 #
b11100010 $
b000100011 %
b011100010 &
1'
b01000110 -
#71
0'
#72
b00100100 #
b11100011 $
b000100100 %
b011100011 &
1'
b01010110 -
#73
0'
#74
b00100101 #
b11100100 $
b000100101 %
b011100100 &
1'
b01100110 -
#75
0'
#76
b00100110 #
b11100101 $
b000100110 %
b011100101 &
1'
b01110110 -
#77
0'
#78
b00100111 #
b11100110 $
b000100111 %
b011100110 &
1'
b10000110 -
#79
0'
#80
b00101000 #
b11100111 $
b000101000 %
b011100111 &
1'
b10010011 -
#81
0'
#82
b00101001 #
b11101000 $
b000101001 %
b011101000 &
1'
b10011111 -
#83
0'
#84
b00101010 #
b11101001 $
b000101010 %
b011101001 &
1'
b01010111 -
#85
0'
#86
b00101011 #
b11101010 $
b000101011 %
b011101010 &
1'
b01000000 -
#87
0'
#88
b00101100 #
b11101011 $
b000101100 %
b011101011 &
1'
b00110110 -
#89
0'
#90
b00101101 #
b11101100 $
b000101101 %
b011101100 &
1'
b00101100 -
#91
0'
#92
b00101110 #
b11101101 $
b000101110 %
b011101101 &
1'
b00100111 -
#93
0'
#94
b00101111 #
b11101110 $
b000101111 %
b011101110 &
1'
b00100110 -
#95
0'
#96
b00110000 #
b11101111 $
b000110000 %
b011101111 &
1'
b00101011 -
#97
0'
#98
b00110001 #
b11110000 $
b000110001 %
b011110000 &
1'
b00110100 -
#99
0'
#100
b00110010 #
b11110001 $
b000110010 %
b011110001 &
1'
b00111111 -
#101
0'
#102
b00110011 #
b11110010 $
b000110011 %
b011110010 &
1'
b01001101 -
#103
0'
#104
b00110100 #
b11110011 $
b000110100 %
b011110011 &
1'
b01011110 -
#105
0'
#106
b00110101 #
b11110100 $
b000110101 %
b011110100 &
1'
b01101101 -
#107
0'
#108
b00110110 #
b11110101 $
b000110110 %
b011110101 &
1'
b01111100 -
#109
0'
#110
b00110111 #
b11110110 $
b000110111 %
b011110110 &
1'
b10001100 -
#111
0'
#112
b00111000 #
b11110111 $
b000111000 %
b011110111 &
1'
b10011000 -
#113
0'
#114
b00111001 #
b11111000 $
b000111001 %
b011111000 &
1'
b10100010 -
#115
0'
#116
b00111010 #
b11111001 $
b000111010 %
b011111001 &
1'
b10101010 -
#117
0'
#118
b00111011 #
b11111010 $
b000111011 %
b011111010 &
1'
b10101101 -
#119
0'
#120
b00111100 #
b11111011 $
b000111100 %
b011111011 &
1'
b10101011 -
#121
0'
#122
b00111101 #
b11111100 $
b000111101 %
b011111100 &
1'
b10100100 -
#123
0'
#124
b00111110 #
b11111101 $
b000111110 %
b011111101 &
1'
b10011000 -
#125
0'
#126
b00111111 #
b11111110 $
b000111111 %
b011111110 &
1'
b10000111 -
#127
0'
#128
b01000000 #
b11111111 $
b001000000 %
b011111111 &
1'
b01110100 -
#129
0'
#130
b01000001 #
b00000000 $
b001000001 %
b000000000 &
1'
b01100010 -
#131
0'
#132
b01000010 #
b00000001 $
b001000010 %
b000000001 &
1'
b01010000 -
#133
0'
#134
b01000011 #
b00000010 $
b001000011 %
b000000010 &
1'
b01000010 -
#135
0'
#136
b01000100 #
b00000011 $
b001000100 %
b000000011 &
1'
b00110101 -
#137
0'
#138
b01000101 #
b00000100 $
b001000101 %
b000000100 &
1'
b00101100 -
#139
0'
#140
b01000110 #
b00000101 $
b001000110 %
b000000101 &
1'
b00101000 -
#141
0'
#142
b01000111 #
b00000110 $
b001000111 %
b000000110 &
1'
b00100110 -
#143
0'
#144
b01001000 #
b00000111 $
b001001000 %
b000000111 &
1'
b00101011 -
#145
0'
#146
b01001001 #
b00001000 $
b001001001 %
b000001000 &
1'
b00110101 -
#147
0'
#148
b01001010 #
b00001001 $
b001001010 %
b000001001 &
1'
b01000000 -
#149
0'
#150
b01001011 #
b00001010 $
b001001011 %
b000001010 &
1'
b01010000 -
#151
0'
#152
b01001100 #
b00001011 $
b001001100 %
b000001011 &
1'
b01100000 -
#153
0'
#154
b01001101 #
b00001100 $
b001001101 %
b000001100 &
1'
b01110000 -
#155
0'
#156
b01001110 #
b00001101 $
b001001110 %
b000001101 &
1'
b10000000 -
#157
0'
#158
b01001111 #
b00001110 $
b001001111 %
b000001110 &
1'
b10001111 -
#159
0'
#160
b01010000 #
b00001111 $
b001010000 %
b000001111 &
1'
b10011010 -
#161
0'
#162
b01010001 #
b00010000 $
b001010001 %
b000010000 &
1'
b10100100 -
#163
0'
#164
b01010010 #
b00010001 $
b001010010 %
b000010001 &
1'
b10101011 -
#165
0'
#166
b01010011 #
b00010010 $
b001010011 %
b000010010 &
1'
b10101100 -
#167
0'
#168
b01010100 #
b00010011 $
b001010100 %
b000010011 &
1'
b10101001 -
#169
0'
#170
b01010101 #
b00010100 $
b001010101 %
b000010100 &
1'
b10100000 -
#171
0'
#172
b01010110 #
b00010101 $
b001010110 %
b000010101 &
1'
b10010011 -
#173
0'
#174
b01010111 #
b00010110 $
b001010111 %
b000010110 &
1'
b10000100 -
#175
0'
#176
b01011000 #
b00010111 $
b001011000 %
b000010111 &
1'
b01110001 -
#177
0'
#178
b01011001 #
b00011000 $
b001011001 %
b000011000 &
1'
b01011111 -
#179
0'
#180
b01011010 #
b00011001 $
b001011010 %
b000011001 &
1'
b01001110 -
#181
0'
#182
b01011011 #
b00011010 $
b001011011 %
b000011010 &
1'
b00111111 -
#183
0'
#184
b01011100 #
b00011011 $
b001011100 %
b000011011 &
1'
b00110011 -
#185
0'
#186
b01011101 #
b00011100 $
b001011101 %
b000011100 &
1'
b00101011 -
#187
0'
#188
b01011110 #
b00011101 $
b001011110 %
b000011101 &
1'
b00100110 -
#189
0'
#190
b01011111 #
b00011110 $
b001011111 %
b000011110 &
1'
b00100111 -
#191
0'
#192
b01100000 #
b00011111 $
b001100000 %
b000011111 &
1'
b00101101 -
#193
0'
#194
b01100001 #
b00100000 $
b001100001 %
b000100000 &
1'
b00110111 -
#195
0'
#196
b01100010 #
b00100001 $
b001100010 %
b000100001 &
1'
b01000100 -
#197
0'
#198
b01100011 #
b00100010 $
b001100011 %
b000100010 &
1'
b01010100 -
#199
0'
#200
b01100100 #
b00100011 $
b001100100 %
b000100011 &
1'
b01100010 -
#201
0'
#202
b01100101 #
b00100100 $
b001100101 %
b000100100 &
1'
b01110101 -
#203
0'
#204
b01100110 #
b00100101 $
b001100110 %
b000100101 &
1'
b10000101 -
#205
0'
#206
b01100111 #
b00100110 $
b001100111 %
b000100110 &
1'
b10010011 -
#207
0'
#208
b01101000 #
b00100111 $
b001101000 %
b000100111 &
1'
b10100001 -
#209
0'
#210
b01101001 #
b00101000 $
b001101001 %
b000101000 &
1'
b10101010 -
#211
0'
#212
b01101010 #
b00101001 $
b001101010 %
b000101001 &
1'
b10110000 -
#213
0'
#214
b01101011 #
b00101010 $
b001101011 %
b000101010 &
1'
b10101111 -
#215
0'
#216
b01101100 #
b00101011 $
b001101100 %
b000101011 &
1'
b10101011 -
#217
0'
#218
b01101101 #
b00101100 $
b001101101 %
b000101100 &
1'
b10100001 -
#219
0'
#220
b01101110 #
b00101101 $
b001101110 %
b000101101 &
1'
b10010101 -
#221
0'
#222
b01101111 #
b00101110 $
b001101111 %
b000101110 &
1'
b10000100 -
#223
0'
#224
b01110000 #
b00101111 $
b001110000 %
b000101111 &
1'
b01110001 -
#225
0'
#226
b01110001 #
b00110000 $
b001110001 %
b000110000 &
1'
b01011111 -
#227
0'
#228
b01110010 #
b00110001 $
b001110010 %
b000110001 &
1'
b01001110 -
#229
0'
#230
b01110011 #
b00110010 $
b001110011 %
b000110010 &
1'
b01000000 -
#231
0'
#232
b01110100 #
b00110011 $
b001110100 %
b000110011 &
1'
b00110100 -
#233
0'
#234
b01110101 #
b00110100 $
b001110101 %
b000110100 &
1'
b00101101 -
#235
0'
#236
b01110110 #
b00110101 $
b001110110 %
b000110101 &
1'
b00101010 -
#237
0'
#238
b01110111 #
b00110110 $
b001110111 %
b000110110 &
1'
b00101011 -
#239
0'
#240
b01111000 #
b00110111 $
b001111000 %
b000110111 &
1'
b00110001 -
#241
0'
#242
b01111001 #
b00111000 $
b001111001 %
b000111000 &
1'
b00111011 -
#243
0'
#244
b01111010 #
b00111001 $
b001111010 %
b000111001 &
1'
b01001001 -
#245
0'
#246
b01111011 #
b00111010 $
b001111011 %
b000111010 &
1'
b01011001 -
#247
0'
#248
b01111100 #
b00111011 $
b001111100 %
b000111011 &
1'
b01101010 -
#249
0'
#250
b01111101 #
b00111100 $
b001111101 %
b000111100 &
1'
b01111011 -
#251
0'
#252
b01111110 #
b00111101 $
b001111110 %
b000111101 &
1'
b10001011 -
#253
0'
#254
b01111111 #
b00111110 $
b001111111 %
b000111110 &
1'
b10011000 -
#255
0'
#256
b10000000 #
b00111111 $
b010000000 %
b000111111 &
1'
b10100011 -
#257
0'
#258
b10000001 #
b01000000 $
b010000001 %
b001000000 &
1'
b10101101 -
#259
0'
#260
b10000010 #
b01000001 $
b010000010 %
b001000001 &
1'
b10101111 -
#261
0'
#262
b10000011 #
b01000010 $
b010000011 %
b001000010 &
1'
b10110000 -
#263
0'
#264
b10000100 #
b01000011 $
b010000100 %
b001000011 &
1'
b10101010 -
#265
0'
#266
b10000101 #
b01000100 $
b010000101 %
b001000100 &
1'
b10100000 -
#267
0'
#268
b10000110 #
b01000101 $
b010000110 %
b001000101 &
1'
b10010001 -
#269
0'
#270
b10000111 #
b01000110 $
b010000111 %
b001000110 &
1'
b10000000 -
#271
0'
#272
b10001000 #
b01000111 $
b010001000 %
b001000111 &
1'
b01101101 -
#273
0'
#274
b10001001 #
b01001000 $
b010001001 %
b001001000 &
1'
b01011110 -
#275
0'
#276
b10001010 #
b01001001 $
b010001010 %
b001001001 &
1'
b01001101 -
#277
0'
#278
b10001011 #
b01001010 $
b010001011 %
b001001010 &
1'
b00111111 -
#279
0'
#280
b10001100 #
b01001011 $
b010001100 %
b001001011 &
1'
b00110110 -
#281
0'
#282
b10001101 #
b01001100 $
b010001101 %
b001001100 &
1'
b00101111 -
#283
0'
#284
b10001110 #
b01001101 $
b010001110 %
b001001101 &
1'
b00101100 -
#285
0'
#286
b10001111 #
b01001110 $
b010001111 %
b001001110 &
1'
b00101110 -
#287
0'
#288
b10010000 #
b01001111 $
b010010000 %
b001001111 &
1'
b00110110 -
#289
0'
#290
b10010001 #
b01010000 $
b010010001 %
b001010000 &
1'
b01000010 -
#291
0'
#292
b10010010 #
b01010001 $
b010010010 %
b001010001 &
1'
b01010000 -
#293
0'
#294
b10010011 #
b01010010 $
b010010011 %
b001010010 &
1'
b01011110 -
#295
0'
#296
b10010100 #
b01010011 $
b010010100 %
b001010011 &
1'
b01101110 -
#297
0'
#298
b10010101 #
b01010100 $
b010010101 %
b001010100 &
1'
b01111111 -
#299
0'
#300
b10010110 #
b01010101 $
b010010110 %
b001010101 &
1'
b10001100 -
#301
0'
#302
b10010111 #
b01010110 $
b010010111 %
b001010110 &
1'
b10011000 -
#303
0'
#304
b10011000 #
b01010111 $
b010011000 %
b001010111 &
1'
b10100011 -
#305
0'
#306
b10011001 #
b01011000 $
b010011001 %
b001011000 &
1'
b10101011 -
#307
0'
#308
b10011010 #
b01011001 $
b010011010 %
b001011001 &
1'
b10110000 -
#309
0'
#310
b10011011 #
b01011010 $
b010011011 %
b001011010 &
1'
b10101101 -
#311
0'
#312
b10011100 #
b01011011 $
b010011100 %
b001011011 &
1'
b10100111 -
#313
0'
#314
b10011101 #
b01011100 $
b010011101 %
b001011100 &
1'
b10011100 -
#315
0'
#316
b10011110 #
b01011101 $
b010011110 %
b001011101 &
1'
b10001100 -
#317
0'
#318
b10011111 #
b01011110 $
b010011111 %
b001011110 &
1'
b01111011 -
#319
0'
#320
b10100000 #
b01011111 $
b010100000 %
b001011111 &
1'
b01101010 -
#321
0'
#322
b10100001 #
b01100000 $
b010100001 %
b001100000 &
1'
b01011000 -
#323
0'
#324
b10100010 #
b01100001 $
b010100010 %
b001100001 &
1'
b01001000 -
#325
0'
#326
b10100011 #
b01100010 $
b010100011 %
b001100010 &
1'
b00111011 -
#327
0'
#328
b10100100 #
b01100011 $
b010100100 %
b001100011 &
1'
b00110000 -
#329
0'
#330
b10100101 #
b01100100 $
b010100101 %
b001100100 &
1'
b00101010 -
#331
0'
#332
b10100110 #
b01100101 $
b010100110 %
b001100101 &
1'
b00101001 -
#333
0'
#334
b10100111 #
b01100110 $
b010100111 %
b001100110 &
1'
b00101101 -
#335
0'
#336
b10101000 #
b01100111 $
b010101000 %
b001100111 &
1'
b00110100 -
#337
0'
#338
b10101001 #
b01101000 $
b010101001 %
b001101000 &
1'
b01000000 -
#339
0'
#340
b10101010 #
b01101001 $
b010101010 %
b001101001 &
1'
b01001101 -
#341
0'
#342
b10101011 #
b01101010 $
b010101011 %
b001101010 &
1'
b01011101 -
#343
0'
#344
b10101100 #
b01101011 $
b010101100 %
b001101011 &
1'
b01101101 -
#345
0'
#346
b10101101 #
b01101100 $
b010101101 %
b001101100 &
1'
b01111110 -
#347
0'
#348
b10101110 #
b01101101 $
b010101110 %
b001101101 &
1'
b10001101 -
#349
0'
#350
b10101111 #
b01101110 $
b010101111 %
b001101110 &
1'
b10011010 -
#351
0'
#352
b10110000 #
b01101111 $
b010110000 %
b001101111 &
1'
b10100100 -
#353
0'
#354
b10110001 #
b01110000 $
b010110001 %
b001110000 &
1'
b10101011 -
#355
0'
#356
b10110010 #
b01110001 $
b010110010 %
b001110001 &
1'
b10101110 -
#357
0'
#358
b10110011 #
b01110010 $
b010110011 %
b001110010 &
1'
b10101100 -
#359
0'
#360
b10110100 #
b01110011 $
b010110100 %
b001110011 &
1'
b10100110 -
#361
0'
#362
b10110101 #
b01110100 $
b010110101 %
b001110100 &
1'
b10011001 -
#363
0'
#364
b10110110 #
b01110101 $
b010110110 %
b001110101 &
1'
b10001001 -
#365
0'
#366
b10110111 #
b01110110 $
b010110111 %
b001110110 &
1'
b01110110 -
#367
0'
#368
b10111000 #
b01110111 $
b010111000 %
b001110111 &
1'
b01100011 -
#369
0'
#370
b10111001 #
b01111000 $
b010111001 %
b001111000 &
1'
b01010010 -
#371
0'
#372
b10111010 #
b01111001 $
b010111010 %
b001111001 &
1'
b01000010 -
#373
0'
#374
b10111011 #
b01111010 $
b010111011 %
b001111010 &
1'
b00110111 -
#375
0'
#376
b10111100 #
b01111011 $
b010111100 %
b001111011 &
1'
b00101110 -
#377
0'
#378
b10111101 #
b01111100 $
b010111101 %
b001111100 &
1'
b00101000 -
#379
0'
#380
b10111110 #
b01111101 $
b010111110 %
b001111101 &
1'
#381
0'
#382
b10111111 #
b01111110 $
b010111111 %
b001111110 &
1'
b00101101 -
#383
0'
#384
b11000000 #
b01111111 $
b011000000 %
b001111111 &
1'
b00110110 -
#385
0'
#386
b11000001 #
b10000000 $
b011000001 %
b010000000 &
1'
b01000010 -
b01110110 .
#387
0'
#388
b11000010 #
b10000001 $
b011000010 %
b010000001 &
1'
b01010001 -
b01011111 .
#389
0'
#390
b11000011 #
b10000010 $
b011000011 %
b010000010 &
1'
b01100001 -
b01001111 .
#391
0'
#392
b11000100 #
b10000011 $
b011000100 %
b010000011 &
1'
b01110010 -
b01000000 .
#393
0'
#394
b11000101 #
b10000100 $
b011000101 %
b010000100 &
1'
b10000001 -
b00110100 .
#395
0'
#396
b11000110 #
b10000101 $
b011000110 %
b010000101 &
1'
b10001111 -
b00101011 .
#397
0'
#398
b11000111 #
b10000110 $
b011000111 %
b010000110 &
1'
b10011011 -
b00100111 .
#399
0'
#400
b11001000 #
b10000111 $
b011001000 %
b010000111 &
1'
b10100100 -
b00101000 .
#401
0'
#402
b11001001 #
b10001000 $
b011001001 %
b010001000 &
1'
b10101100 -
b00101101 .
#403
0'
#404
b11001010 #
b10001001 $
b011001010 %
b010001001 &
1'
b10101101 -
b00110110 .
#405
0'
#406
b11001011 #
b10001010 $
b011001011 %
b010001010 &
1'
b10101010 -
b01000011 .
#407
0'
#408
b11001100 #
b10001011 $
b011001100 %
b010001011 &
1'
b10100000 -
b01010011 .
#409
0'
#410
b11001101 #
b10001100 $
b011001101 %
b010001100 &
1'
b10010011 -
b01100010 .
#411
0'
#412
b11001110 #
b10001101 $
b011001110 %
b010001101 &
1'
b10000010 -
b01110011 .
#413
0'
#414
b11001111 #
b10001110 $
b011001111 %
b010001110 &
1'
b01110000 -
b10000011 .
#415
0'
#416
b11010000 #
b10001111 $
b011010000 %
b010001111 &
1'
b01011101 -
b10010010 .
#417
0'
#418
b11010001 #
b10010000 $
b011010001 %
b010010000 &
1'
b01001100 -
b10011110 .
#419
0'
#420
b11010010 #
b10010001 $
b011010010 %
b010010001 &
1'
b00111101 -
b10101000 .
#421
0'
#422
b11010011 #
b10010010 $
b011010011 %
b010010010 &
1'
b00110001 -
b10101101 .
#423
0'
#424
b11010100 #
b10010011 $
b011010100 %
b010010011 &
1'
b00101000 -
b10101111 .
#425
0'
#426
b11010101 #
b10010100 $
b011010101 %
b010010100 &
1'
b00100100 -
b10101010 .
#427
0'
#428
b11010110 #
b10010101 $
b011010110 %
b010010101 &
1'
b10100000 .
#429
0'
#430
b11010111 #
b10010110 $
b011010111 %
b010010110 &
1'
b00101011 -
b10010011 .
#431
0'
#432
b11011000 #
b10010111 $
b011011000 %
b010010111 &
1'
b00110101 -
b10000001 .
#433
0'
#434
b11011001 #
b10011000 $
b011011001 %
b010011000 &
1'
b01000010 -
b01101110 .
#435
0'
#436
b11011010 #
b10011001 $
b011011010 %
b010011001 &
1'
b01010001 -
b01011100 .
#437
0'
#438
b11011011 #
b10011010 $
b011011011 %
b010011010 &
1'
b01100011 -
b01001010 .
#439
0'
#440
b11011100 #
b10011011 $
b011011100 %
b010011011 &
1'
b01110001 -
b00111100 .
#441
0'
#442
b11011101 #
b10011100 $
b011011101 %
b010011100 &
1'
b10000010 -
b00110001 .
#443
0'
#444
b11011110 #
b10011101 $
b011011110 %
b010011101 &
1'
b10010001 -
b00101011 .
#445
0'
#446
b11011111 #
b10011110 $
b011011111 %
b010011110 &
1'
b10011101 -
b00101000 .
#447
0'
#448
b11100000 #
b10011111 $
b011100000 %
b010011111 &
1'
b10101000 -
#449
0'
#450
b11100001 #
b10100000 $
b011100001 %
b010100000 &
1'
b10101110 -
b00101110 .
#451
0'
#452
b11100010 #
b10100001 $
b011100010 %
b010100001 &
1'
b10101111 -
b00111001 .
#453
0'
#454
b11100011 #
b10100010 $
b011100011 %
b010100010 &
1'
b10101011 -
b01000110 .
#455
0'
#456
b11100100 #
b10100011 $
b011100100 %
b010100011 &
1'
b10100001 -
b01010110 .
#457
0'
#458
b11100101 #
b10100100 $
b011100101 %
b010100100 &
1'
b10010100 -
b01100110 .
#459
0'
#460
b11100110 #
b10100101 $
b011100110 %
b010100101 &
1'
b10000011 -
b01110110 .
#461
0'
#462
b11100111 #
b10100110 $
b011100111 %
b010100110 &
1'
b01110000 -
b10000110 .
#463
0'
#464
b11101000 #
b10100111 $
b011101000 %
b010100111 &
1'
b01011101 -
b10010011 .
#465
0'
#466
b11101001 #
b10101000 $
b011101001 %
b010101000 &
1'
b01001100 -
b10011111 .
#467
0'
#468
b11101010 #
b10101001 $
b011101010 %
b010101001 &
1'
b00111100 -
b01010111 .
#469
0'
#470
b11101011 #
b10101010 $
b011101011 %
b010101010 &
1'
b00110010 -
b01000000 .
#471
0'
#472
b11101100 #
b10101011 $
b011101100 %
b010101011 &
1'
b00101001 -
b00110110 .
#473
0'
#474
b11101101 #
b10101100 $
b011101101 %
b010101100 &
1'
b00100110 -
b00101100 .
#475
0'
#476
b11101110 #
b10101101 $
b011101110 %
b010101101 &
1'
b00100111 -
b00100111 .
#477
0'
#478
b11101111 #
b10101110 $
b011101111 %
b010101110 &
1'
b00101101 -
b00100110 .
#479
0'
#480
b11110000 #
b10101111 $
b011110000 %
b010101111 &
1'
b00110111 -
b00101011 .
#481
0'
#482
b11110001 #
b10110000 $
b011110001 %
b010110000 &
1'
b01000110 -
b00110100 .
#483
0'
#484
b11110010 #
b10110001 $
b011110010 %
b010110001 &
1'
b01010101 -
b00111111 .
#485
0'
#486
b11110011 #
b10110010 $
b011110011 %
b010110010 &
1'
b01100110 -
b01001101 .
#487
0'
#488
b11110100 #
b10110011 $
b011110100 %
b010110011 &
1'
b01111000 -
b01011110 .
#489
0'
#490
b11110101 #
b10110100 $
b011110101 %
b010110100 &
1'
b10000111 -
b01101101 .
#491
0'
#492
b11110110 #
b10110101 $
b011110110 %
b010110101 &
1'
b10010110 -
b01111100 .
#493
0'
#494
b11110111 #
b10110110 $
b011110111 %
b010110110 &
1'
b10011111 -
b10001100 .
#495
0'
#496
b11111000 #
b10110111 $
b011111000 %
b010110111 &
1'
b10101001 -
b10011000 .
#497
0'
#498
b11111001 #
b10111000 $
b011111001 %
b010111000 &
1'
b10101110 -
b10100010 .
#499
0'
#500
b11111010 #
b10111001 $
b011111010 %
b010111001 &
1'
b10101010 .
#501
0'
#502
b11111011 #
b10111010 $
b011111011 %
b010111010 &
1'
b10101000 -
b10101101 .
#503
0'
#504
b11111100 #
b10111011 $
b011111100 %
b010111011 &
1'
b10011101 -
b10101011 .
#505
0'
#506
b11111101 #
b10111100 $
b011111101 %
b010111100 &
1'
b10001100 -
b10100100 .
#507
0'
#508
b11111110 #
b10111101 $
b011111110 %
b010111101 &
1'
b01111011 -
b10011000 .
#509
0'
#510
b11111111 #
b10111110 $
b011111111 %
b010111110 &
1'
b01100111 -
b10000111 .
#511
0'
#512
b00000000 #
b10111111 $
b000000000 %
b010111111 &
1'
b01010110 -
b01110100 .
#513
0'
#514
b00000001 #
b11000000 $
b000000001 %
b011000000 &
1'
b01000101 -
b01100010 .
#515
0'
#516
b00000010 #
b11000001 $
b000000010 %
b011000001 &
1'
b00111000 -
b01010000 .
#517
0'
#518
b00000011 #
b11000010 $
b000000011 %
b011000010 &
1'
b00101101 -
b01000010 .
#519
0'
#520
b00000100 #
b11000011 $
b000000100 %
b011000011 &
1'
b00100110 -
b00110101 .
#521
0'
#522
b00000101 #
b11000100 $
b000000101 %
b011000100 &
1'
b00100100 -
b00101100 .
#523
0'
#524
b00000110 #
b11000101 $
b000000110 %
b011000101 &
1'
b00100101 -
b00101000 .
#525
0'
#526
b00000111 #
b11000110 $
b000000111 %
b011000110 &
1'
b00101110 -
b00100110 .
#527
0'
#528
b00001000 #
b11000111 $
b000001000 %
b011000111 &
1'
b00111001 -
b00101011 .
#529
0'
#530
b00001001 #
b11001000 $
b000001001 %
b011001000 &
1'
b01001000 -
b00110101 .
#531
0'
#532
b00001010 #
b11001001 $
b000001010 %
b011001001 &
1'
b01011001 -
b01000000 .
#533
0'
#534
b00001011 #
b11001010 $
b000001011 %
b011001010 &
1'
b01101001 -
b01010000 .
#535
0'
#536
b00001100 #
b11001011 $
b000001100 %
b011001011 &
1'
b01111001 -
b01100000 .
#537
0'
