task2/rom.sv
module rom #(
    parameter ADDRESS_WIDTH = 8,
    parameter DATA_WIDTH = 8
)(
    input logic clk,
    input logic [ADDRESS_WIDTH-1:0] addr1,
    input logic [ADDRESS_WIDTH-1:0] addr2,
    output logic [DATA_WIDTH-1:0] dout1,
    output logic [DATA_WIDTH-1:0] dout2,

);
// 3-bit vector with a depth of 2^8 bits
logic [DATA_WIDTH-1:0] rom_array [2**ADDRESS_WIDTH-1:0];

// Initialise memory
initial begin
    $display("Loading data to ROM");
    $readmemh("sinerom.mem",rom_array);
end

always_ff @(posedge clk) begin
    dout1 <= rom_array[addr1];
    dout2 <= rom_array[addr2];
end

endmodule

task2/counter.sv
module counter #(
    // bits in counter set to 8 bits
    parameter WIDTH = 8
)(
    // interface signals
    input logic clk, //clk
    input logic rst, //reset
    input logic en, // enable
    input logic [WIDTH-1:0] incr,//increment
    output logic [WIDTH-1:0] count1, //count output
    output logic [WIDTH-1:0] count2 //count output

);
// indicates that this is a clocked circuit

always_ff @(posedge clk) 
if(rst) begin
    count1 <= 0;
    count2 <= 0;
end
else begin
    count1 <= count1+ 1'b1;
    count2 <= count1+ incr;
end


endmodule

task2/sinegen.sv
module sinegen #(
    parameter D_WIDTH = 8,
    parameter A_WIDTH = 8
)(
    input logic clk,
    input logic rst,
    input logic en,
    input logic [D_WIDTH-1:0] incr,
    output logic [D_WIDTH-1:0] dout1,
    output logic [D_WIDTH-1:0] dout2,
);

// connecting variable
logic [D_WIDTH-1:0] addr1;
logic [D_WIDTH-1:0] addr2;


counter addrCounter (
    .clk (clk),
    .rst(rst),
    .en(en),
    .incr(incr),
    .count1(addr1),
    .count2(addr2)
);

rom sinerom(
    .clk(clk),
    .addr1(addr1),
    .addr2(addr2),
    .dout1(dout1),
    .dout2(dout2)
);
endmodule

task2/sinegen.vcd
$version Generated by VerilatedVcd $end
$date Sat Oct 29 17:09:46 2022 $end
$timescale 1ps $end

 $scope module TOP $end
  $var wire  1 # clk $end
  $var wire  8 ' dout1 [7:0] $end
  $var wire  8 ( dout2 [7:0] $end
  $var wire  1 % en $end
  $var wire  8 & incr [7:0] $end
  $var wire  1 $ rst $end
  $scope module sinegen $end
   $var wire 32 + A_WIDTH [31:0] $end
   $var wire 32 + D_WIDTH [31:0] $end
   $var wire  8 ) addr1 [7:0] $end
   $var wire  8 * addr2 [7:0] $end
   $var wire  1 # clk $end
   $var wire  8 ' dout1 [7:0] $end
   $var wire  8 ( dout2 [7:0] $end
   $var wire  1 % en $end
   $var wire  8 & incr [7:0] $end
   $var wire  1 $ rst $end
   $scope module addrCounter $end
    $var wire 32 + WIDTH [31:0] $end
    $var wire  1 # clk $end
    $var wire  8 ) count1 [7:0] $end
    $var wire  8 * count2 [7:0] $end
    $var wire  1 % en $end
    $var wire  8 & incr [7:0] $end
    $var wire  1 $ rst $end
   $upscope $end
   $scope module sinerom $end
    $var wire 32 + ADDRESS_WIDTH [31:0] $end
    $var wire 32 + DATA_WIDTH [31:0] $end
    $var wire  8 ) addr1 [7:0] $end
    $var wire  8 * addr2 [7:0] $end
    $var wire  1 # clk $end
    $var wire  8 ' dout1 [7:0] $end
    $var wire  8 ( dout2 [7:0] $end
   $upscope $end
  $upscope $end
 $upscope $end
$enddefinitions $end


#0
1#
0$
1%
b00000001 &
b00000000 '
b00000000 (
b00000000 )
b00000000 *
b00000000000000000000000000001000 +
#1
0#
#2
1#
b00000000 &
b11111110 '
b11111110 (
b00000001 )
b00000001 *
#3
0#
#4
1#
b11111101 '
b11111101 (
b00000010 )
#5
0#
#6
1#
b00000011 )
b00000010 *
#7
0#
#8
1#
b00000100 )
b00000011 *
#9
0#
#10
1#
b00000101 )
b00000100 *
#11
0#
#12
1#
b00000110 )
b00000101 *
#13
0#
#14
1#
b11111100 '
b00000111 )
b00000110 *
#15
0#
#16
1#
b11111100 (
b00001000 )
b00000111 *
#17
0#
#18
1#
b11111011 '
b00001001 )
b00001000 *
#19
0#
#20
1#
b11111010 '
b11111011 (
b00001010 )
b00001001 *
#21
0#
#22
1#
b11111010 (
b00001011 )
b00001010 *
#23
0#
#24
1#
b11111001 '
b00001100 )
b00001011 *
#25
0#
#26
1#
b11111000 '
b11111001 (
b00001101 )
b00001100 *
#27
0#
#28
1#
b11110111 '
b11111000 (
b00001110 )
b00001101 *
#29
0#
#30
1#
b11110110 '
b11110111 (
b00001111 )
b00001110 *
#31
0#
#32
1#
b11110101 '
b11110110 (
b00010000 )
b00001111 *
#33
0#
#34
1#
b11110100 '
b11110101 (
b00010001 )
b00010000 *
#35
0#
#36
1#
b11110011 '
b11110100 (
b00010010 )
b00010001 *
#37
0#
#38
1#
b11110001 '
b11110011 (
b00010011 )
b00010010 *
#39
0#
#40
1#
b11110000 '
b11110001 (
b00010100 )
b00010011 *
#41
0#
#42
1#
b11101111 '
b11110000 (
b00010101 )
b00010100 *
#43
0#
#44
1#
b11101101 '
b11101111 (
b00010110 )
b00010101 *
#45
0#
#46
1#
b11101011 '
b11101101 (
b00010111 )
b00010110 *
#47
0#
#48
1#
b11101010 '
b11101011 (
b00011000 )
b00010111 *
#49
0#
#50
1#
b11101000 '
b11101010 (
b00011001 )
b00011000 *
#51
0#
#52
1#
b11100110 '
b11101000 (
b00011010 )
b00011001 *
#53
0#
#54
1#
b11100101 '
b11100110 (
b00011011 )
b00011010 *
#55
0#
#56
1#
b11100011 '
b11100101 (
b00011100 )
b00011011 *
#57
0#
#58
1#
b11100001 '
b11100011 (
b00011101 )
b00011100 *
#59
0#
#60
1#
b11011111 '
b11100001 (
b00011110 )
b00011101 *
#61
0#
#62
1#
b11011101 '
b11011111 (
b00011111 )
b00011110 *
#63
0#
#64
1#
b11011010 '
b11011101 (
b00100000 )
b00011111 *
#65
0#
#66
1#
b11011000 '
b11011010 (
b00100001 )
b00100000 *
#67
0#
#68
1#
b11010110 '
b11011000 (
b00100010 )
b00100001 *
#69
0#
#70
1#
b11010100 '
b11010110 (
b00100011 )
b00100010 *
#71
0#
#72
1#
b11010001 '
b11010100 (
b00100100 )
b00100011 *
#73
0#
#74
1#
b11001111 '
b11010001 (
b00100101 )
b00100100 *
#75
0#
#76
1#
b11001101 '
b11001111 (
b00100110 )
b00100101 *
#77
0#
#78
1#
b11001010 '
b11001101 (
b00100111 )
b00100110 *
#79
0#
#80
1#
b11001000 '
b11001010 (
b00101000 )
b00100111 *
#81
0#
#82
1#
b11000101 '
b11001000 (
b00101001 )
b00101000 *
#83
0#
#84
1#
b11000010 '
b11000101 (
b00101010 )
b00101001 *
#85
0#
#86
1#
b11000000 '
b11000010 (
b00101011 )
b00101010 *
#87
0#
#88
1#
b10111101 '
b11000000 (
b00101100 )
b00101011 *
#89
0#
#90
1#
b10111010 '
b10111101 (
b00101101 )
b00101100 *
#91
0#
#92
1#
b10111000 '
b10111010 (
b00101110 )
b00101101 *
#93
0#
#94
1#
b10110101 '
b10111000 (
b00101111 )
b00101110 *
#95
0#
#96
1#
b10110010 '
b10110101 (
b00110000 )
b00101111 *
#97
0#
#98
1#
b10101111 '
b10110010 (
b00110001 )
b00110000 *
#99
0#
#100
1#
b10101100 '
b10101111 (
b00110010 )
b00110001 *
#101
0#
#102
1#
b10101001 '
b10101100 (
b00110011 )
b00110010 *
#103
0#
#104
1#
b10100110 '
b10101001 (
b00110100 )
b00110011 *
#105
0#
#106
1#
b10100011 '
b10100110 (
b00110101 )
b00110100 *
#107
0#
#108
1#
b10100000 '
b10100011 (
b00110110 )
b00110101 *
#109
0#
#110
1#
b10011101 '
b10100000 (
b00110111 )
b00110110 *
#111
0#
#112
1#
b10011010 '
b10011101 (
b00111000 )
b00110111 *
#113
0#
#114
1#
b10010111 '
b10011010 (
b00111001 )
b00111000 *
#115
0#
#116
1#
b10010100 '
b10010111 (
b00111010 )
b00111001 *
#117
0#
#118
1#
b10010001 '
b10010100 (
b00111011 )
b00111010 *
#119
0#
#120
1#
b10001110 '
b10010001 (
b00111100 )
b00111011 *
#121
0#
#122
1#
b10001011 '
b10001110 (
b00111101 )
b00111100 *
#123
0#
#124
1#
b10001000 '
b10001011 (
b00111110 )
b00111101 *
#125
0#
#126
1#
b10000101 '
b10001000 (
b00111111 )
b00111110 *
#127
0#
#128
1#
b10000010 '
b10000101 (
b01000000 )
b00111111 *
#129
0#
#130
1#
b01111110 '
b10000010 (
b01000001 )
b01000000 *
#131
0#
#132
1#
b01111011 '
b01111110 (
b01000010 )
b01000001 *
#133
0#
#134
1#
b01111000 '
b01111011 (
b01000011 )
b01000010 *
#135
0#
#136
1#
b01110101 '
b01111000 (
b01000100 )
b01000011 *
#137
0#
#138
1#
b01110010 '
b01110101 (
b01000101 )
b01000100 *
#139
0#
#140
1#
b01101111 '
b01110010 (
b01000110 )
b01000101 *
#141
0#
#142
1#
b01101100 '
b01101111 (
b01000111 )
b01000110 *
#143
0#
#144
1#
b01101001 '
b01101100 (
b01001000 )
b01000111 *
#145
0#
#146
1#
b01100110 '
b01101001 (
b01001001 )
b01001000 *
#147
0#
#148
1#
b01100011 '
b01100110 (
b01001010 )
b01001001 *
#149
0#
#150
1#
b01100000 '
b01100011 (
b01001011 )
b01001010 *
#151
0#
#152
1#
b01011101 '
b01100000 (
b01001100 )
b01001011 *
#153
0#
#154
1#
b01011010 '
b01011101 (
b01001101 )
b01001100 *
#155
0#
#156
1#
b01010111 '
b01011010 (
b01001110 )
b01001101 *
#157
0#
#158
1#
b01010100 '
b01010111 (
b01001111 )
b01001110 *
#159
0#
#160
1#
b01010001 '
b01010100 (
b01010000 )
b01001111 *
#161
0#
#162
1#
b01001110 '
b01010001 (
b01010001 )
b01010000 *
#163
0#
#164
1#
b01001011 '
b01001110 (
b01010010 )
b01010001 *
#165
0#
#166
1#
b01001000 '
b01001011 (
b01010011 )
b01010010 *
#167
0#
#168
1#
b01000101 '
b01001000 (
b01010100 )
b01010011 *
#169
0#
#170
1#
b01000011 '
b01000101 (
b01010101 )
b01010100 *
#171
0#
#172
1#
b01000000 '
b01000011 (
b01010110 )
b01010101 *
#173
0#
#174
1#
b00111101 '
b01000000 (
b01010111 )
b01010110 *
#175
0#
#176
1#
b00111011 '
b00111101 (
b01011000 )
b01010111 *
#177
0#
#178
1#
b00111000 '
b00111011 (
b01011001 )
b01011000 *
#179
0#
#180
1#
b00110101 '
b00111000 (
b01011010 )
b01011001 *
#181
0#
#182
1#
b00110011 '
b00110101 (
b01011011 )
b01011010 *
#183
0#
#184
1#
b00110000 '
b00110011 (
b01011100 )
b01011011 *
#185
0#
#186
1#
b00101110 '
b00110000 (
b01011101 )
b01011100 *
#187
0#
#188
1#
b00101100 '
b00101110 (
b01011110 )
b01011101 *
#189
0#
#190
1#
b00101001 '
b00101100 (
b01011111 )
b01011110 *
#191
0#
#192
1#
b00100111 '
b00101001 (
b01100000 )
b01011111 *
#193
0#
#194
1#
b00100101 '
b00100111 (
b01100001 )
b01100000 *
#195
0#
#196
1#
b00100011 '
b00100101 (
b01100010 )
b01100001 *
#197
0#
#198
1#
b00100000 '
b00100011 (
b01100011 )
b01100010 *
#199
0#
#200
1#
b00011110 '
b00100000 (
b01100100 )
b01100011 *
#201
0#
#202
1#
b00011100 '
b00011110 (
b01100101 )
b01100100 *
#203
0#
#204
1#
b00011010 '
b00011100 (
b01100110 )
b01100101 *
#205
0#
#206
1#
b00011000 '
b00011010 (
b01100111 )
b01100110 *
#207
0#
#208
1#
b00010111 '
b00011000 (
b01101000 )
b01100111 *
#209
0#
#210
1#
b00010101 '
b00010111 (
b01101001 )
b01101000 *
#211
0#
#212
1#
b00010011 '
b00010101 (
b01101010 )
b01101001 *
#213
0#
#214
1#
b00010010 '
b00010011 (
b01101011 )
b01101010 *
#215
0#
#216
1#
b00010000 '
b00010010 (
b01101100 )
b01101011 *
#217
0#
#218
1#
b00001110 '
b00010000 (
b01101101 )
b01101100 *
#219
0#
#220
1#
b00001101 '
b00001110 (
b01101110 )
b01101101 *
#221
0#
#222
1#
b00001100 '
b00001101 (
b01101111 )
b01101110 *
#223
0#
#224
1#
b00001010 '
b00001100 (
b01110000 )
b01101111 *
#225
0#
#226
1#
b00001001 '
b00001010 (
b01110001 )
b01110000 *
#227
0#
#228
1#
b00001000 '
b00001001 (
b01110010 )
b01110001 *
#229
0#
#230
1#
b00000111 '
b00001000 (
b01110011 )
b01110010 *
#231
0#
#232
1#
b00000110 '
b00000111 (
b01110100 )
b01110011 *
#233
0#
#234
1#
b00000101 '
b00000110 (
b01110101 )
b01110100 *
#235
0#
#236
1#
b00000100 '
b00000101 (
b01110110 )
b01110101 *
#237
0#
#238
1#
b00000011 '
b00000100 (
b01110111 )
b01110110 *
#239
0#
#240
1#
b00000011 (
b01111000 )
b01110111 *
#241
0#
#242
1#
b00000010 '
b01111001 )
b01111000 *
#243
0#
#244
1#
b00000001 '
b00000010 (
b01111010 )
b01111001 *
#245
0#
#246
1#
b00000001 (
b01111011 )
b01111010 *
#247
0#
#248
1#
b00000000 '
b01111100 )
b01111011 *
#249
0#
#250
1#
b00000000 (
b01111101 )
b01111100 *
#251
0#
#252
1#
b01111110 )
b01111101 *
#253
0#
#254
1#
b01111111 )
b01111110 *
#255
0#
#256
1#
b10000000 )
b01111111 *
#257
0#
#258
1#
b10000001 )
b10000000 *
#259
0#
#260
1#
b10000010 )
b10000001 *
#261
0#
#262
1#
b10000011 )
b10000010 *
#263
0#
#264
1#
b10000100 )
b10000011 *
#265
0#
#266
1#
b10000101 )
b10000100 *
#267
0#
#268
1#
b10000110 )
b10000101 *
#269
0#
#270
1#
b00000001 '
b10000111 )
b10000110 *
#271
0#
#272
1#
b00000001 (
b10001000 )
b10000111 *
#273
0#
#274
1#
b00000010 '
b10001001 )
b10001000 *
#275
0#
#276
1#
b00000011 '
b00000010 (
b10001010 )
b10001001 *
#277
0#
#278
1#
b00000011 (
b10001011 )
b10001010 *
#279
0#
#280
1#
b00000100 '
b10001100 )
b10001011 *
#281
0#
#282
1#
b00000101 '
b00000100 (
b10001101 )
b10001100 *
#283
0#
#284
1#
b00000110 '
b00000101 (
b10001110 )
b10001101 *
#285
0#
#286
1#
b00000111 '
b00000110 (
b10001111 )
b10001110 *
#287
0#
#288
1#
b00001000 '
b00000111 (
b10010000 )
b10001111 *
#289
0#
#290
1#
b00001001 '
b00001000 (
b10010001 )
b10010000 *
#291
0#
#292
1#
b00001010 '
b00001001 (
b10010010 )
b10010001 *
#293
0#
#294
1#
b00001100 '
b00001010 (
b10010011 )
b10010010 *
#295
0#
#296
1#
b00001101 '
b00001100 (
b10010100 )
b10010011 *
#297
0#
#298
1#
b00001110 '
b00001101 (
b10010101 )
b10010100 *
#299
0#
#300
1#
b00010000 '
b00001110 (
b10010110 )
b10010101 *
#301
0#
#302
1#
b00010010 '
b00010000 (
b10010111 )
b10010110 *
#303
0#
#304
1#
b00010011 '
b00010010 (
b10011000 )
b10010111 *
#305
0#
#306
1#
b00010101 '
b00010011 (
b10011001 )
b10011000 *
#307
0#
#308
1#
b00010111 '
b00010101 (
b10011010 )
b10011001 *
#309
0#
#310
1#
b00011000 '
b00010111 (
b10011011 )
b10011010 *
#311
0#
#312
1#
b00011010 '
b00011000 (
b10011100 )
b10011011 *
#313
0#
#314
1#
b00011100 '
b00011010 (
b10011101 )
b10011100 *
#315
0#
#316
1#
b00011110 '
b00011100 (
b10011110 )
b10011101 *
#317
0#
#318
1#
b00100000 '
b00011110 (
b10011111 )
b10011110 *
#319
0#
#320
1#
b00100011 '
b00100000 (
b10100000 )
b10011111 *
#321
0#
#322
1#
b00100101 '
b00100011 (
b10100001 )
b10100000 *
#323
0#
#324
1#
b00100111 '
b00100101 (
b10100010 )
b10100001 *
#325
0#
#326
1#
b00101001 '
b00100111 (
b10100011 )
b10100010 *
#327
0#
#328
1#
b00101100 '
b00101001 (
b10100100 )
b10100011 *
#329
0#
#330
1#
b00101110 '
b00101100 (
b10100101 )
b10100100 *
#331
0#
#332
1#
b00110000 '
b00101110 (
b10100110 )
b10100101 *
#333
0#
#334
1#
b00110011 '
b00110000 (
b10100111 )
b10100110 *
#335
0#
#336
1#
b00110101 '
b00110011 (
b10101000 )
b10100111 *
#337
0#
#338
1#
b00111000 '
b00110101 (
b10101001 )
b10101000 *
#339
0#
#340
1#
b00111011 '
b00111000 (
b10101010 )
b10101001 *
#341
0#
#342
1#
b00111101 '
b00111011 (
b10101011 )
b10101010 *
#343
0#
#344
1#
b01000000 '
b00111101 (
b10101100 )
b10101011 *
#345
0#
#346
1#
b01000011 '
b01000000 (
b10101101 )
b10101100 *
#347
0#
#348
1#
b01000101 '
b01000011 (
b10101110 )
b10101101 *
#349
0#
#350
1#
b01001000 '
b01000101 (
b10101111 )
b10101110 *
#351
0#
#352
1#
b01001011 '
b01001000 (
b10110000 )
b10101111 *
#353
0#
#354
1#
b01001110 '
b01001011 (
b10110001 )
b10110000 *
#355
0#
#356
1#
b01010001 '
b01001110 (
b10110010 )
b10110001 *
#357
0#
#358
1#
b01010100 '
b01010001 (
b10110011 )
b10110010 *
#359
0#
#360
1#
b01010111 '
b01010100 (
b10110100 )
b10110011 *
#361
0#
#362
1#
b01011010 '
b01010111 (
b10110101 )
b10110100 *
#363
0#
#364
1#
b01011101 '
b01011010 (
b10110110 )
b10110101 *
#365
0#
#366
1#
b01100000 '
b01011101 (
b10110111 )
b10110110 *
#367
0#
#368
1#
b01100011 '
b01100000 (
b10111000 )
b10110111 *
#369
0#
#370
1#
b01100110 '
b01100011 (
b10111001 )
b10111000 *
#371
0#
#372
1#
b01101001 '
b01100110 (
b10111010 )
b10111001 *
#373
0#
#374
1#
b01101100 '
b01101001 (
b10111011 )
b10111010 *
#375
0#
#376
1#
b01101111 '
b01101100 (
b10111100 )
b10111011 *
#377
0#
#378
1#
b01110010 '
b01101111 (
b10111101 )
b10111100 *
#379
0#
#380
1#
b01110101 '
b01110010 (
b10111110 )
b10111101 *
#381
0#
#382
1#
b01111000 '
b01110101 (
b10111111 )
b10111110 *
#383
0#
#384
1#
b01111011 '
b01111000 (
b11000000 )
b10111111 *
#385
0#
#386
1#
b01111111 '
b01111011 (
b11000001 )
b11000000 *
#387
0#
#388
1#
b10000010 '
b01111111 (
b11000010 )
b11000001 *
#389
0#
#390
1#
b10000101 '
b10000010 (
b11000011 )
b11000010 *
#391
0#
#392
1#
b10001000 '
b10000101 (
b11000100 )
b11000011 *
#393
0#
#394
1#
b10001011 '
b10001000 (
b11000101 )
b11000100 *
#395
0#
#396
1#
b10001110 '
b10001011 (
b11000110 )
b11000101 *
#397
0#
#398
1#
b10010001 '
b10001110 (
b11000111 )
b11000110 *
#399
0#
#400
1#
b10010100 '
b10010001 (
b11001000 )
b11000111 *
#401
0#
#402
1#
b10010111 '
b10010100 (
b11001001 )
b11001000 *
#403
0#
#404
1#
b10011010 '
b10010111 (
b11001010 )
b11001001 *
#405
0#
#406
1#
b10011101 '
b10011010 (
b11001011 )
b11001010 *
#407
0#
#408
1#
b10100000 '
b10011101 (
b11001100 )
b11001011 *
#409
0#
#410
1#
b10100011 '
b10100000 (
b11001101 )
b11001100 *
#411
0#
#412
1#
b10100110 '
b10100011 (
b11001110 )
b11001101 *
#413
0#
#414
1#
b10101001 '
b10100110 (
b11001111 )
b11001110 *
#415
0#
#416
1#
b10101100 '
b10101001 (
b11010000 )
b11001111 *
#417
0#
#418
1#
b10101111 '
b10101100 (
b11010001 )
b11010000 *
#419
0#
#420
1#
b10110010 '
b10101111 (
b11010010 )
b11010001 *
#421
0#
#422
1#
b10110101 '
b10110010 (
b11010011 )
b11010010 *
#423
0#
#424
1#
b10111000 '
b10110101 (
b11010100 )
b11010011 *
#425
0#
#426
1#
b10111010 '
b10111000 (
b11010101 )
b11010100 *
#427
0#
#428
1#
b10111101 '
b10111010 (
b11010110 )
b11010101 *
#429
0#
#430
1#
b11000000 '
b10111101 (
b11010111 )
b11010110 *
#431
0#
#432
1#
b11000010 '
b11000000 (
b11011000 )
b11010111 *
#433
0#
#434
1#
b11000101 '
b11000010 (
b11011001 )
b11011000 *
#435
0#
#436
1#
b11001000 '
b11000101 (
b11011010 )
b11011001 *
#437
0#
#438
1#
b11001010 '
b11001000 (
b11011011 )
b11011010 *
#439
0#
#440
1#
b11001101 '
b11001010 (
b11011100 )
b11011011 *
#441
0#
#442
1#
b11001111 '
b11001101 (
b11011101 )
b11011100 *
#443
0#
#444
1#
b11010001 '
b11001111 (
b11011110 )
b11011101 *
#445
0#
#446
1#
b11010100 '
b11010001 (
b11011111 )
b11011110 *
#447
0#
#448
1#
b00000001 &
b11010110 '
b11010100 (
b11100000 )
b11011111 *
#449
0#
#450
1#
b11011000 '
b11010110 (
b11100001 )
b11100001 *
#451
0#
#452
1#
b11011010 '
b11011010 (
b11100010 )
b11100010 *
#453
0#
#454
1#
b11011101 '
b11011101 (
b11100011 )
b11100011 *
#455
0#
#456
1#
b11011111 '
b11011111 (
b11100100 )
b11100100 *
#457
0#
#458
1#
b11100001 '
b11100001 (
b11100101 )
b11100101 *
#459
0#
#460
1#
b11100011 '
b11100011 (
b11100110 )
b11100110 *
#461
0#
#462
1#
b11100101 '
b11100101 (
b11100111 )
b11100111 *
#463
0#
#464
1#
b11100110 '
b11100110 (
b11101000 )
b11101000 *
#465
0#
#466
1#
b11101000 '
b11101000 (
b11101001 )
b11101001 *
#467
0#
#468
1#
b11101010 '
b11101010 (
b11101010 )
b11101010 *
#469
0#
#470
1#
b11101011 '
b11101011 (
b11101011 )
b11101011 *
#471
0#
#472
1#
b11101101 '
b11101101 (
b11101100 )
b11101100 *
#473
0#
#474
1#
b11101111 '
b11101111 (
b11101101 )
b11101101 *
#475
0#
#476
1#
b11110000 '
b11110000 (
b11101110 )
b11101110 *
#477
0#
#478
1#
b11110001 '
b11110001 (
b11101111 )
b11101111 *
#479
0#
#480
1#
b11110011 '
b11110011 (
b11110000 )
b11110000 *
#481
0#
#482
1#
b11110100 '
b11110100 (
b11110001 )
b11110001 *
#483
0#
#484
1#
b11110101 '
b11110101 (
b11110010 )
b11110010 *
#485
0#
#486
1#
b11110110 '
b11110110 (
b11110011 )
b11110011 *
#487
0#
#488
1#
b11110111 '
b11110111 (
b11110100 )
b11110100 *
#489
0#
#490
1#
b11111000 '
b11111000 (
b11110101 )
b11110101 *
#491
0#
#492
1#
b11111001 '
b11111001 (
b11110110 )
b11110110 *
#493
0#
#494
1#
b11111010 '
b11111010 (
b11110111 )
b11110111 *
#495
0#
#496
1#
b11111000 )
b11111000 *
#497
0#
#498
1#
b11111011 '
b11111011 (
b11111001 )
b11111001 *
#499
0#
#500
1#
b11111100 '
b11111100 (
b11111010 )
b11111010 *
#501
0#
#502
1#
b11111011 )
b11111011 *
#503
0#
#504
1#
b11111101 '
b11111101 (
b11111100 )
b11111100 *
#505
0#
#506
1#
b11111101 )
b11111101 *
#507
0#
#508
1#
b11111110 )
b11111110 *
#509
0#
#510
1#
b11111111 )
b11111111 *
#511
0#
#512
1#
b00000000 )
b00000000 *
#513
0#
#514
1#
b11111110 '
b11111110 (
b00000001 )
b00000001 *
#515
0#
#516
1#
b11111101 '
b11111101 (
b00000010 )
b00000010 *
#517
0#
#518
1#
b00000011 )
b00000011 *
#519
0#
#520
1#
b00000100 )
b00000100 *
#521
0#
#522
1#
b00000101 )
b00000101 *
#523
0#
#524
1#
b00000110 )
b00000110 *
#525
0#
#526
1#
b11111100 '
b11111100 (
b00000111 )
b00000111 *
#527
0#
#528
1#
b00001000 )
b00001000 *
#529
0#
#530
1#
b11111011 '
b11111011 (
b00001001 )
b00001001 *
#531
0#
#532
1#
b11111010 '
b11111010 (
b00001010 )
b00001010 *
#533
0#
#534
1#
b00001011 )
b00001011 *
#535
0#
#536
1#
b11111001 '
b11111001 (
b00001100 )
b00001100 *
#537
0#
#538
1#
b11111000 '
b11111000 (
b00001101 )
b00001101 *
#539
0#
#540
1#
b11110111 '
b11110111 (
b00001110 )
b00001110 *
#541
0#
#542
1#
b11110110 '
b11110110 (
b00001111 )
b00001111 *
#543
0#
#544
1#
b11110101 '
b11110101 (
b00010000 )
b00010000 *
#545
0#
#546
1#
b11110100 '
b11110100 (
b00010001 )
b00010001 *
#547
0#
#548
1#
b11110011 '
b11110011 (
b00010010 )
b00010010 *
#549
0#
#550
1#
b11110001 '
b11110001 (
b00010011 )
b00010011 *
#551
0#
#552
1#
b11110000 '
b11110000 (
b00010100 )
b00010100 *
#553
0#
#554
1#
b11101111 '
b11101111 (
b00010101 )
b00010101 *
#555
0#
#556
1#
b11101101 '
b11101101 (
b00010110 )
b00010110 *
#557
0#
#558
1#
b11101011 '
b11101011 (
b00010111 )
b00010111 *
#559
0#
#560
1#
b00000010 &
b11101010 '
b11101010 (
b00011000 )
b00011000 *
#561
0#
#562
1#
b11101000 '
b11101000 (
b00011001 )
b00011010 *
#563
0#
#564
1#
b11100110 '
b11100101 (
b00011010 )
b00011011 *
#565
0#
#566
1#
b11100101 '
b11100011 (
b00011011 )
b00011100 *
#567
0#
#568
1#
b11100011 '
b11100001 (
b00011100 )
b00011101 *
#569
0#
#570
1#
b11100001 '
b11011111 (
b00011101 )
b00011110 *
#571
0#
#572
1#
b11011111 '
b11011101 (
b00011110 )
b00011111 *
#573
0#
#574
1#
b11011101 '
b11011010 (
b00011111 )
b00100000 *
#575
0#
#576
1#
b11011010 '
b11011000 (
b00100000 )
b00100001 *
#577
0#
#578
1#
b11011000 '
b11010110 (
b00100001 )
b00100010 *
#579
0#
#580
1#
b11010110 '
b11010100 (
b00100010 )
b00100011 *
#581
0#
#582
1#
b11010100 '
b11010001 (
b00100011 )
b00100100 *
#583
0#
#584
1#
b11010001 '
b11001111 (
b00100100 )
b00100101 *
#585
0#
#586
1#
b11001111 '
b11001101 (
b00100101 )
b00100110 *
#587
0#
#588
1#
b11001101 '
b11001010 (
b00100110 )
b00100111 *
#589
0#
#590
1#
b11001010 '
b11001000 (
b00100111 )
b00101000 *
#591
0#
#592
1#
b11001000 '
b11000101 (
b00101000 )
b00101001 *
#593
0#
#594
1#
b11000101 '
b11000010 (
b00101001 )
b00101010 *
#595
0#
#596
1#
b00000011 &
b11000010 '
b11000000 (
b00101010 )
b00101011 *
#597
0#
#598
1#
b11000000 '
b10111101 (
b00101011 )
b00101101 *
#599
0#
#600
1#
b10111101 '
b10111000 (
b00101100 )
b00101110 *
#601
0#
#602
1#
b10111010 '
b10110101 (
b00101101 )
b00101111 *
#603
0#
#604
1#
b10111000 '
b10110010 (
b00101110 )
b00110000 *
#605
0#
#606
1#
b10110101 '
b10101111 (
b00101111 )
b00110001 *
#607
0#
#608
1#
b10110010 '
b10101100 (
b00110000 )
b00110010 *
#609
0#
#610
1#
b10101111 '
b10101001 (
b00110001 )
b00110011 *
#611
0#
#612
1#
b10101100 '
b10100110 (
b00110010 )
b00110100 *
#613
0#
#614
1#
b10101001 '
b10100011 (
b00110011 )
b00110101 *
#615
0#
#616
1#
b10100110 '
b10100000 (
b00110100 )
b00110110 *
#617
0#
#618
1#
b10100011 '
b10011101 (
b00110101 )
b00110111 *
#619
0#
#620
1#
b10100000 '
b10011010 (
b00110110 )
b00111000 *
#621
0#
#622
1#
b10011101 '
b10010111 (
b00110111 )
b00111001 *
#623
0#
#624
1#
b10011010 '
b10010100 (
b00111000 )
b00111010 *
#625
0#
#626
1#
b10010111 '
b10010001 (
b00111001 )
b00111011 *
#627
0#
#628
1#
b10010100 '
b10001110 (
b00111010 )
b00111100 *
#629
0#
#630
1#
b10010001 '
b10001011 (
b00111011 )
b00111101 *
#631
0#
#632
1#
b10001110 '
b10001000 (
b00111100 )
b00111110 *
#633
0#
#634
1#
b10001011 '
b10000101 (
b00111101 )
b00111111 *
#635
0#
#636
1#
b10001000 '
b10000010 (
b00111110 )
b01000000 *
#637
0#
#638
1#
b00000100 &
b10000101 '
b01111110 (
b00111111 )
b01000001 *
#639
0#
#640
1#
b10000010 '
b01111011 (
b01000000 )
b01000011 *
#641
0#
#642
1#
b01111110 '
b01110101 (
b01000001 )
b01000100 *
#643
0#
#644
1#
b01111011 '
b01110010 (
b01000010 )
b01000101 *
#645
0#
#646
1#
b01111000 '
b01101111 (
b01000011 )
b01000110 *
#647
0#
#648
1#
b01110101 '
b01101100 (
b01000100 )
b01000111 *
#649
0#
#650
1#
b01110010 '
b01101001 (
b01000101 )
b01001000 *
#651
0#
#652
1#
b01101111 '
b01100110 (
b01000110 )
b01001001 *
#653
0#
#654
1#
b01101100 '
b01100011 (
b01000111 )
b01001010 *
#655
0#
#656
1#
b01101001 '
b01100000 (
b01001000 )
b01001011 *
#657
0#
#658
1#
b01100110 '
b01011101 (
b01001001 )
b01001100 *
#659
0#
#660
1#
b01100011 '
b01011010 (
b01001010 )
b01001101 *
#661
0#
#662
1#
b01100000 '
b01010111 (
b01001011 )
b01001110 *
#663
0#
#664
1#
b00000101 &
b01011101 '
b01010100 (
b01001100 )
b01001111 *
#665
0#
#666
1#
b01011010 '
b01010001 (
b01001101 )
b01010001 *
#667
0#
#668
1#
b01010111 '
b01001011 (
b01001110 )
b01010010 *
#669
0#
#670
1#
b01010100 '
b01001000 (
b01001111 )
b01010011 *
#671
0#
#672
1#
b01010001 '
b01000101 (
b01010000 )
b01010100 *
#673
0#
#674
1#
b01001110 '
b01000011 (
b01010001 )
b01010101 *
#675
0#
#676
1#
b01001011 '
b01000000 (
b01010010 )
b01010110 *
#677
0#
#678
1#
b01001000 '
b00111101 (
b01010011 )
b01010111 *
#679
0#
#680
1#
b01000101 '
b00111011 (
b01010100 )
b01011000 *
#681
0#
#682
1#
b01000011 '
b00111000 (
b01010101 )
b01011001 *
#683
0#
#684
1#
b01000000 '
b00110101 (
b01010110 )
b01011010 *
#685
0#
